pyexcel_ods3/__init__.py
pyexcel_ods3/odsr.py
pyexcel_ods3/odsw.py
pyexcel_ods3-0.6.1.dist-info/LICENSE
pyexcel_ods3-0.6.1.dist-info/METADATA
pyexcel_ods3-0.6.1.dist-info/WHEEL
pyexcel_ods3-0.6.1.dist-info/top_level.txt
pyexcel_ods3-0.6.1.dist-info/RECORD
