Metadata-Version: 2.1
Name: pyexcel-ods3
Version: 0.6.1
Summary: A wrapper library to read, manipulate and write data in ods format
Home-page: https://github.com/pyexcel/pyexcel-ods3
Author: C.W.
Author-email: info@pyexcel.org
License: New BSD
Download-URL: https://github.com/pyexcel/pyexcel-ods3/archive/0.6.1.tar.gz
Keywords: python,ods
Platform: UNKNOWN
Classifier: Topic :: Software Development :: Libraries
Classifier: Programming Language :: Python
Classifier: Intended Audience :: Developers
Classifier: Programming Language :: Python :: 3 :: Only
Classifier: Programming Language :: Python :: 3.6
Classifier: Programming Language :: Python :: 3.7
Classifier: Programming Language :: Python :: 3.8
Classifier: License :: OSI Approved :: BSD License
Requires-Python: >=3.6
License-File: LICENSE
